odoo/addons/mrp_analytic_child_mo/README.rst
odoo/addons/mrp_analytic_child_mo/__init__.py
odoo/addons/mrp_analytic_child_mo/__manifest__.py
odoo/addons/mrp_analytic_child_mo/i18n/mrp_analytic_child_mo.pot
odoo/addons/mrp_analytic_child_mo/models/__init__.py
odoo/addons/mrp_analytic_child_mo/models/mrp_production.py
odoo/addons/mrp_analytic_child_mo/readme/CONTRIBUTORS.rst
odoo/addons/mrp_analytic_child_mo/readme/DESCRIPTION.rst
odoo/addons/mrp_analytic_child_mo/static/description/icon.png
odoo/addons/mrp_analytic_child_mo/static/description/index.html
odoo/addons/mrp_analytic_child_mo/tests/__init__.py
odoo/addons/mrp_analytic_child_mo/tests/test_mrp_analytic.py
odoo14_addon_mrp_analytic_child_mo-14.0.1.0.1.dist-info/METADATA
odoo14_addon_mrp_analytic_child_mo-14.0.1.0.1.dist-info/WHEEL
odoo14_addon_mrp_analytic_child_mo-14.0.1.0.1.dist-info/top_level.txt
odoo14_addon_mrp_analytic_child_mo-14.0.1.0.1.dist-info/RECORD
